base_datos/__init__.py
base_datos/admin.py
base_datos/apps.py
base_datos/boot_django.py
base_datos/models.py
base_datos/tests.py
base_datos/views.py
base_datos/migrations/__init__.py
django_models_monocontact-1.0.dist-info/LICENSE
django_models_monocontact-1.0.dist-info/METADATA
django_models_monocontact-1.0.dist-info/WHEEL
django_models_monocontact-1.0.dist-info/top_level.txt
django_models_monocontact-1.0.dist-info/RECORD
